torch_gists/__init__.py
torch_gists/utils.py
torch_gists/models/__init__.py
torch_gists/models/mobilenetv2.py
torch_gists/models/resnet.py
torch_gists/models/vgg.py
torch_gists-0.0.0.2.dist-info/LICENSE
torch_gists-0.0.0.2.dist-info/METADATA
torch_gists-0.0.0.2.dist-info/WHEEL
torch_gists-0.0.0.2.dist-info/top_level.txt
torch_gists-0.0.0.2.dist-info/RECORD
