Metadata-Version: 2.1
Name: torch-gists
Version: 0.0.0.2
Summary: A collection of models and utilities for pytorch
Home-page: https://github.com/rishikanthc/torch-gists
Author: Rishikanth
Author-email: r3chandr@ucsd.edu
License: UNKNOWN
Project-URL: Bug Tracker, https://github.com/rishikanthc/torch-gists/issues
Platform: UNKNOWN
Classifier: Programming Language :: Python :: 3
Classifier: License :: OSI Approved :: MIT License
Classifier: Operating System :: OS Independent
Requires-Python: >=3.6
